akinator/__init__.pyi
akinator/__init__.py
akinator/akinator.pypy39-pp73-darwin.so
akinator/py.typed
akinator.py-0.2.5.dist-info/RECORD
akinator.py-0.2.5.dist-info/WHEEL
akinator.py-0.2.5.dist-info/METADATA
akinator.py-0.2.5.dist-info/license_files/LICENSE
