Metadata-Version: 2.1
Name: akinator.py
Version: 0.2.5
Requires-Dist: sphinx; extra == 'docs'
Requires-Dist: furo; extra == 'docs'
Requires-Dist: sphinxext-opengraph; extra == 'docs'
Requires-Dist: sphinx-copybutton; extra == 'docs'
Provides-Extra: docs
License-File: LICENSE
Summary: Python bindings for akinator-rs
Keywords: akinator,python,async,game,pyo3
Home-Page: https://github.com/Tom-the-Bomb/akinator.py
Author: Tom the Bomb
License: MIT
Requires-Python: >=3.7
Project-URL: documentation, https://akinatorpy.readthedocs.io/en/latest/
Project-URL: repository, https://github.com/Tom-the-Bomb/akinator.py
Project-URL: homepage, https://github.com/Tom-the-Bomb/akinator.py
